MANIFEST.in
README.txt
setup.cfg
setup.py
src/mobi/__init__.py
src/mobi.caching.egg-info/PKG-INFO
src/mobi.caching.egg-info/SOURCES.txt
src/mobi.caching.egg-info/dependency_links.txt
src/mobi.caching.egg-info/namespace_packages.txt
src/mobi.caching.egg-info/requires.txt
src/mobi.caching.egg-info/top_level.txt
src/mobi/caching/__init__.py
src/mobi/caching/backend.py
src/mobi/caching/cache.py
src/mobi/caching/tests/doctest_cache.py