Metadata-Version: 1.0
Name: mobi.caching
Version: 1.0
Summary: Cache utils
Home-page: infrae.com
Author: Infrae
Author-email: info@infrae.com
License: BSD
Platform: UNKNOWN
